selahx/__init__.py
selahx/cli.py
selahx/client.py
selahx/ec2/setup.sh
selahx/save_files.py
selahx/server.py
selahx-0.1.4.dist-info/METADATA
selahx-0.1.4.dist-info/WHEEL
selahx-0.1.4.dist-info/entry_points.txt
selahx-0.1.4.dist-info/licenses/LICENSE
selahx-0.1.4.dist-info/RECORD
