Metadata-Version: 2.4
Name: selahx
Version: 0.1.4
Summary: Remote Access Tool — Fast and lightweight CLI experience.
License: MIT
License-File: LICENSE
Author: Abiy
Author-email: abiy.dema@gmail.com
Requires-Python: >=3.8,<4.0
Classifier: License :: OSI Approved :: MIT License
Classifier: Programming Language :: Python :: 3
Classifier: Programming Language :: Python :: 3.8
Classifier: Programming Language :: Python :: 3.9
Classifier: Programming Language :: Python :: 3.10
Classifier: Programming Language :: Python :: 3.11
Classifier: Programming Language :: Python :: 3.12
Classifier: Programming Language :: Python :: 3.13
Classifier: Programming Language :: Python :: 3.14
Requires-Dist: argparse (>=1.4.0,<2.0.0)
Requires-Dist: cffi (>=2.0.0,<3.0.0)
Requires-Dist: mouseinfo (>=0.1.3,<0.2.0)
Requires-Dist: mss (>=10.1.0,<11.0.0)
Requires-Dist: numpy (>=2,<2.3.0)
Requires-Dist: opencv-python (>=4.12.0.88,<5.0.0.0)
Requires-Dist: pyautogui (>=0.9.54,<0.10.0)
Requires-Dist: pycparser (>=2.23,<3.0)
Requires-Dist: pygetwindow (>=0.0.9,<0.0.10)
Requires-Dist: pymsgbox (>=2.0.1,<3.0.0)
Requires-Dist: pyobjc-core (>=12.0,<13.0)
Requires-Dist: pyobjc-framework-cocoa (>=12.0,<13.0)
Requires-Dist: pyobjc-framework-quartz (>=12.0,<13.0)
Requires-Dist: pyperclip (>=1.11.0,<2.0.0)
Requires-Dist: pyrect (>=0.2.0,<0.3.0)
Requires-Dist: pyscreeze (>=1.0.1,<2.0.0)
Requires-Dist: python3-xlib (>=0.15,<0.16)
Requires-Dist: pytweening (>=1.2.0,<2.0.0)
Requires-Dist: readchar (>=4.2.1,<5.0.0)
Requires-Dist: rubicon-objc (>=0.5.2,<0.6.0)
Requires-Dist: scipy (>=1.16.3,<2.0.0)
Requires-Dist: sounddevice (>=0.5.3,<0.6.0)
Requires-Dist: tabulate (>=0.9.0,<0.10.0)
Requires-Dist: typer (>=0.20.0,<0.21.0)
Project-URL: Documentation, https://github.com/Haabiy/selahx#readme
Project-URL: Homepage, https://github.com/Haabiy/selahx
Project-URL: Repository, https://github.com/Haabiy/selahx
